snak.py
snak-0.1.1.dist-info/licenses/LICENSE
snak-0.1.1.dist-info/METADATA
snak-0.1.1.dist-info/WHEEL
snak-0.1.1.dist-info/entry_points.txt
snak-0.1.1.dist-info/top_level.txt
snak-0.1.1.dist-info/RECORD
