Metadata-Version: 2.4
Name: snak
Version: 0.1.1
Summary: Python Standalone Build Management Tool
Author-email: Dmitry Orlov <me@mosquito.su>
License-Expression: MIT
Project-URL: documentation, https://pypi.org/project/snak/
Keywords: python,build,management,standalone,virtualenv
Classifier: Programming Language :: Python :: 3
Classifier: Operating System :: POSIX :: Linux
Classifier: Operating System :: MacOS
Requires-Python: >3.8
License-File: LICENSE
Dynamic: license-file
